adafruit_st7789.py
adafruit_circuitpython_st7789-2.1.3.dist-info/licenses/LICENSE
adafruit_circuitpython_st7789-2.1.3.dist-info/METADATA
adafruit_circuitpython_st7789-2.1.3.dist-info/WHEEL
adafruit_circuitpython_st7789-2.1.3.dist-info/top_level.txt
adafruit_circuitpython_st7789-2.1.3.dist-info/RECORD
